domino_data_capture/__init__.py
domino_data_capture/data_capture_client.py
domino_data_capture/exception.py
domino_data_capture/logger.py
domino_data_capture/utils.py
domino_data_capture-0.1.2.dist-info/LICENSE.txt
domino_data_capture-0.1.2.dist-info/WHEEL
domino_data_capture-0.1.2.dist-info/METADATA
domino_data_capture-0.1.2.dist-info/RECORD
