Metadata-Version: 2.1
Name: domino-data-capture
Version: 0.1.2
Summary: Domino Prediction Client to log prediction data
Home-page: https://github.com/cerebrotech/dmm-data-ingest-client
License: Apache Software License 2.0
Author: Sayan Nayak
Author-email: sayan.nayak@dominodatalab.com
Requires-Python: >=3.7,<4.0
Classifier: Development Status :: 3 - Alpha
Classifier: Intended Audience :: Developers
Classifier: License :: OSI Approved :: Apache Software License
Classifier: License :: Other/Proprietary License
Classifier: Operating System :: OS Independent
Classifier: Programming Language :: Python :: 3
Classifier: Programming Language :: Python :: 3.10
Classifier: Programming Language :: Python :: 3.6
Classifier: Programming Language :: Python :: 3.7
Classifier: Programming Language :: Python :: 3.8
Classifier: Programming Language :: Python :: 3.9
Classifier: Topic :: Software Development :: Libraries :: Python Modules
Requires-Dist: attrs (>=20.1.0,<22.0.0)
Requires-Dist: click (>=8,<9)
Requires-Dist: python-dateutil (>=2.8.0,<3.0.0)
Project-URL: Repository, https://github.com/cerebrotech/dmm-data-ingest-client
